MANIFEST.in
README.md
setup.py
wifileds/__init__.py
wifileds.egg-info/PKG-INFO
wifileds.egg-info/SOURCES.txt
wifileds.egg-info/dependency_links.txt
wifileds.egg-info/top_level.txt
wifileds/limitlessled/README.md
wifileds/limitlessled/__init__.py
wifileds/limitlessled/bridge.py
wifileds/limitlessled/rgb.py
wifileds/limitlessled/rgbw.py
wifileds/limitlessled/white.py
wifileds/limitlessled/effects/__init__.py
wifileds/limitlessled/effects/colorful_strobe.py
wifileds/limitlessled/effects/fade_down.py
wifileds/limitlessled/effects/fade_up.py
wifileds/limitlessled/effects/police_flashers.py
wifileds/limitlessled/effects/pulsating_swells.py
wifileds/limitlessled/effects/rainbow_fade.py
wifileds/limitlessled/effects/strobe.py