Metadata-Version: 1.0
Name: wifileds
Version: 1.0.6
Summary: Library for multiple WiFi LED vendors.
Home-page: http://github.com/joaquincasares/python-wifi-leds
Author: Joaquin Casares
Author-email: joaquin.casares AT gmail.com
License: UNKNOWN
Keywords: wifi led leds l.e.d. light emitting diodes lights lamps bulbs lighting home automation network mesh future LimitlessLED EasyBulb AppLight AppLamp MiLight LEDme dekolight iLight Philips hue LIFX
Platform: UNKNOWN
